colex/__init__.py
colex/_annotations.py
colex/_functions.py
colex/_special.py
colex/color.py
colex/style.py
colex-0.3.2.dist-info/WHEEL
colex-0.3.2.dist-info/METADATA
colex-0.3.2.dist-info/RECORD
