Metadata-Version: 2.3
Name: colex
Version: 0.3.2
Summary: Library with constants and functions for working with colors
Author: Havsalt
Author-email: Havsalt <77575424+Havsalt@users.noreply.github.com>
License: MIT License
Requires-Python: >=3.10
Project-URL: Source, https://github.com/havsalt/colex.git
